<?xml version="1.0" encoding="utf-8" ?>
<dwsync>
<file name="about.php" server="cemma-usc.net" local="130584365076623241" remote="129419676000000000" Dst="2" />
<file name="bookmark.php" server="cemma-usc.net" local="130584365080375771" remote="129419676000000000" Dst="2" />
<file name="exemple00.php" server="cemma-usc.net" local="130584365083577910" remote="129419676000000000" Dst="2" />
<file name="exemple01.php" server="cemma-usc.net" local="130584365086919641" remote="129419676000000000" Dst="2" />
<file name="exemple02.php" server="cemma-usc.net" local="130584365091272552" remote="129419676000000000" Dst="2" />
<file name="exemple03.php" server="cemma-usc.net" local="130584365092083097" remote="129419676000000000" Dst="2" />
<file name="exemple04.php" server="cemma-usc.net" local="130584365096646136" remote="129419676000000000" Dst="2" />
<file name="exemple05.php" server="cemma-usc.net" local="130584365098927676" remote="129419676000000000" Dst="2" />
<file name="exemple06.php" server="cemma-usc.net" local="130584365099688164" remote="129419676000000000" Dst="2" />
<file name="exemple07.php" server="cemma-usc.net" local="130584365103593242" remote="129419676000000000" Dst="2" />
<file name="exemple08.php" server="cemma-usc.net" local="130584365106194975" remote="129419676000000000" Dst="2" />
<file name="exemple09.php" server="cemma-usc.net" local="130584365107165616" remote="129419676000000000" Dst="2" />
<file name="exemple10.php" server="cemma-usc.net" local="130584365111598576" remote="129464604000000000" Dst="2" />
<file name="exemple11.php" server="cemma-usc.net" local="130584365114060216" remote="129419676000000000" Dst="2" />
<file name="exemple12.php" server="cemma-usc.net" local="130584365114960826" remote="129419676000000000" Dst="2" />
<file name="exemple13.php" server="cemma-usc.net" local="130584365118973501" remote="129419676000000000" Dst="2" />
<file name="forms.php" server="cemma-usc.net" local="130584365121194985" remote="129508668000000000" Dst="2" />
<file name="groups.php" server="cemma-usc.net" local="130584365122125603" remote="129466332000000000" Dst="2" />
<file name="js1.php" server="cemma-usc.net" local="130584365125950694" remote="129419676000000000" Dst="2" />
<file name="js2.php" server="cemma-usc.net" local="130584365128201341" remote="129419676000000000" Dst="2" />
<file name="js3.php" server="cemma-usc.net" local="130584365128941835" remote="129419676000000000" Dst="2" />
<file name="qrcode.php" server="cemma-usc.net" local="130584365133034580" remote="129419676000000000" Dst="2" />
<file name="radius.php" server="cemma-usc.net" local="130584365135800586" remote="129419676000000000" Dst="2" />
<file name="regle.php" server="cemma-usc.net" local="130584365136624205" remote="129419676000000000" Dst="2" />
<file name="svg.php" server="cemma-usc.net" local="130584365228385843" remote="129485340000000000" Dst="2" />
<file name="svg_tree.php" server="cemma-usc.net" local="130584365233629349" remote="129485340000000000" Dst="2" />
<file name="svg_tiger.php" server="cemma-usc.net" local="130584365235177238" remote="129485340000000000" Dst="2" />
<file name="ticket.php" server="cemma-usc.net" local="130584365235177238" remote="129485340000000000" Dst="2" />
<file name="utf8.php" server="cemma-usc.net" local="130584365242852554" remote="129467196000000000" Dst="2" />
</dwsync>