<?xml version="1.0" encoding="utf-8" ?>
<dwsync>
<file name="arrow_01.gif" server="cemma-usc.net" local="130584363712554204" remote="127511100000000000" Dst="2" />
<file name="arrow_02.gif" server="cemma-usc.net" local="130584363714275354" remote="127511100000000000" Dst="2" />
<file name="arrow_03.gif" server="cemma-usc.net" local="130584363714275354" remote="127511100000000000" Dst="2" />
<file name="arrow_04.gif" server="cemma-usc.net" local="130584363721200527" remote="127511100000000000" Dst="2" />
<file name="arrow_06.gif" server="cemma-usc.net" local="130584363721200527" remote="127511100000000000" Dst="2" />
<file name="arrow_05.gif" server="cemma-usc.net" local="130584363721981049" remote="127511100000000000" Dst="2" />
<file name="css2.png" server="cemma-usc.net" local="130584363728371241" remote="127511100000000000" Dst="2" />
<file name="dompdf_simple.png" server="cemma-usc.net" local="130584363729933101" remote="127511100000000000" Dst="2" />
<file name="favicon.ico" server="cemma-usc.net" local="130584363729933101" remote="127511100000000000" Dst="2" />
<file name="favicon.png" server="cemma-usc.net" local="130584363736117231" remote="127511100000000000" Dst="2" />
<file name="h_bar.gif" server="cemma-usc.net" local="130584363737578665" remote="127511100000000000" Dst="2" />
<file name="left_arrow.gif" server="cemma-usc.net" local="130584363737578665" remote="127511100000000000" Dst="2" />
<file name="logo.png" server="cemma-usc.net" local="130584363744419300" remote="127511100000000000" Dst="2" />
<file name="logo.xcf" server="cemma-usc.net" local="130584363744429307" remote="127511100000000000" Dst="2" />
<file name="php5-power-micro.png" server="cemma-usc.net" local="130584363745199821" remote="127511100000000000" Dst="2" />
<file name="small_logo.png" server="cemma-usc.net" local="130584363751614113" remote="127511100000000000" Dst="2" />
<file name="star_01.gif" server="cemma-usc.net" local="130584363753095090" remote="127511100000000000" Dst="2" />
<file name="star_02.gif" server="cemma-usc.net" local="130584363753095090" remote="127511100000000000" Dst="2" />
<file name="star_03.gif" server="cemma-usc.net" local="130584363759269214" remote="127511100000000000" Dst="2" />
<file name="star_04.gif" server="cemma-usc.net" local="130584363760730726" remote="127511100000000000" Dst="2" />
<file name="star_05.gif" server="cemma-usc.net" local="130584363760730726" remote="127511100000000000" Dst="2" />
<file name="title.gif" server="cemma-usc.net" local="130584363766934862" remote="127511100000000000" Dst="2" />
<file name="v_bar.gif" server="cemma-usc.net" local="130584363768625991" remote="127511100000000000" Dst="2" />
<file name="xhtml10.png" server="cemma-usc.net" local="130584363768625991" remote="127511100000000000" Dst="2" />
</dwsync>