<?xml version="1.0" encoding="utf-8" ?>
<dwsync>
<file name="accbarex1.php" server="cemma-usc.net" local="130584367283519054" remote="130211100000000000" Dst="2" />
<file name="accbarframeex01.php" server="cemma-usc.net" local="130584367285710521" remote="130211100000000000" Dst="2" />
<file name="accbarframeex02.php" server="cemma-usc.net" local="130584367286781225" remote="130211100000000000" Dst="2" />
<file name="accbarframeex03.php" server="cemma-usc.net" local="130584367290806094" remote="130211100000000000" Dst="2" />
<file name="alphabarex1.php" server="cemma-usc.net" local="130584367293147642" remote="130211100000000000" Dst="2" />
<file name="antispamex01.php" server="cemma-usc.net" local="130584367294027662" remote="130211100000000000" Dst="2" />
<file name="axislabelbkgex01.php" server="cemma-usc.net" local="130584367298675034" remote="130211100000000000" Dst="2" />
<file name="axislabelbkgex02.php" server="cemma-usc.net" local="130584367300986558" remote="130211100000000000" Dst="2" />
<file name="axislabelbkgex03.php" server="cemma-usc.net" local="130584367301817116" remote="130211100000000000" Dst="2" />
<file name="axislabelbkgex04.php" server="cemma-usc.net" local="130584367306411802" remote="130211100000000000" Dst="2" />
<file name="axislabelbkgex05.php" server="cemma-usc.net" local="130584367308633286" remote="130211100000000000" Dst="2" />
<file name="axislabelbkgex06.php" server="cemma-usc.net" local="130584367309453838" remote="130211100000000000" Dst="2" />
<file name="axislabelbkgex07.php" server="cemma-usc.net" local="130584367314007976" remote="130211100000000000" Dst="2" />
<file name="background_type_ex0.php" server="cemma-usc.net" local="130584367316261149" remote="130211100000000000" Dst="2" />
<file name="background_type_ex1.php" server="cemma-usc.net" local="130584367317081705" remote="130211100000000000" Dst="2" />
<file name="background_type_ex2.php" server="cemma-usc.net" local="130584367320914265" remote="130211100000000000" Dst="2" />
<file name="background_type_ex3.php" server="cemma-usc.net" local="130584367323246671" remote="130211100000000000" Dst="2" />
<file name="background_type_ex4.php" server="cemma-usc.net" local="130584367324067219" remote="130211100000000000" Dst="2" />
<file name="backgroundex01.php" server="cemma-usc.net" local="130584367328044636" remote="130211100000000000" Dst="2" />
<file name="backgroundex02.php" server="cemma-usc.net" local="130584367328785135" remote="130211100000000000" Dst="2" />
<file name="backgroundex03.php" server="cemma-usc.net" local="130584367334759117" remote="130211100000000000" Dst="2" />
<file name="balloonex1.php" server="cemma-usc.net" local="130584367337115045" remote="130211100000000000" Dst="2" />
<file name="balloonex2.php" server="cemma-usc.net" local="130584367337115045" remote="130211100000000000" Dst="2" />
<file name="bar2scalesex1.php" server="cemma-usc.net" local="130584367343524028" remote="130211100000000000" Dst="2" />
<file name="bar_csimex1.php" server="cemma-usc.net" local="130584367345375268" remote="130211100000000000" Dst="2" />
<file name="bar_csimex2.php" server="cemma-usc.net" local="130584367345375268" remote="130211100000000000" Dst="2" />
<file name="bar_csimex3.php" server="cemma-usc.net" local="130584367351959677" remote="130211100000000000" Dst="2" />
<file name="barcsim_details.php" server="cemma-usc.net" local="130584367353468389" remote="130211100000000000" Dst="2" />
<file name="barcsim_popup.php" server="cemma-usc.net" local="130584367353468389" remote="130211100000000000" Dst="2" />
<file name="barformatcallbackex1.php" server="cemma-usc.net" local="130584367359762608" remote="130211100000000000" Dst="2" />
<file name="bargradex1.php" server="cemma-usc.net" local="130584367361493962" remote="130211100000000000" Dst="2" />
<file name="bargradex2.php" server="cemma-usc.net" local="130584367361493962" remote="130211100000000000" Dst="2" />
<file name="bargradex3.php" server="cemma-usc.net" local="130584367367818170" remote="130211100000000000" Dst="2" />
<file name="bargradex4.php" server="cemma-usc.net" local="130584367369569339" remote="130211100000000000" Dst="2" />
<file name="bargradex5.php" server="cemma-usc.net" local="130584367369569339" remote="130211100000000000" Dst="2" />
<file name="bargradex6.php" server="cemma-usc.net" local="130584367376677941" remote="130211100000000000" Dst="2" />
<file name="bargradsmallex1.php" server="cemma-usc.net" local="130584367376677941" remote="130211100000000000" Dst="2" />
<file name="bargradsmallex2.php" server="cemma-usc.net" local="130584367377448443" remote="130211100000000000" Dst="2" />
<file name="bargradsmallex3.php" server="cemma-usc.net" local="130584367383653108" remote="130211100000000000" Dst="2" />
<file name="bargradsmallex4.php" server="cemma-usc.net" local="130584367385384256" remote="130211100000000000" Dst="2" />
<file name="bargradsmallex5.php" server="cemma-usc.net" local="130584367385384256" remote="130211100000000000" Dst="2" />
<file name="bargradsmallex6.php" server="cemma-usc.net" local="130584367391773955" remote="130211100000000000" Dst="2" />
<file name="bargradsmallex7.php" server="cemma-usc.net" local="130584367393264951" remote="130211100000000000" Dst="2" />
<file name="bargradsmallex8.php" server="cemma-usc.net" local="130584367393264951" remote="130211100000000000" Dst="2" />
<file name="barimgex1.php" server="cemma-usc.net" local="130584367399959434" remote="130211100000000000" Dst="2" />
<file name="barintex1.php" server="cemma-usc.net" local="130584367401480442" remote="130211100000000000" Dst="2" />
<file name="barintex2.php" server="cemma-usc.net" local="130584367401490449" remote="130211100000000000" Dst="2" />
<file name="barline_csimex1.php" server="cemma-usc.net" local="130584367407817278" remote="130211100000000000" Dst="2" />
<file name="barlinealphaex1.php" server="cemma-usc.net" local="130584367409278257" remote="130211100000000000" Dst="2" />
<file name="barlinefreq_csimex1.php" server="cemma-usc.net" local="130584367409278257" remote="130211100000000000" Dst="2" />
<file name="barlinefreqex1.php" server="cemma-usc.net" local="130584367417530214" remote="130211100000000000" Dst="2" />
<file name="barpatternex1.php" server="cemma-usc.net" local="130584367417540229" remote="130211100000000000" Dst="2" />
<file name="barscalecallbackex1.php" server="cemma-usc.net" local="130584367418430827" remote="130211100000000000" Dst="2" />
<file name="bartutex1.php" server="cemma-usc.net" local="130584367424647449" remote="130211100000000000" Dst="2" />
<file name="bartutex12.php" server="cemma-usc.net" local="130584367427062028" remote="130211100000000000" Dst="2" />
<file name="bartutex2.php" server="cemma-usc.net" local="130584367427062028" remote="130211100000000000" Dst="2" />
<file name="bartutex3.php" server="cemma-usc.net" local="130584367433456290" remote="130211100000000000" Dst="2" />
<file name="bartutex4.php" server="cemma-usc.net" local="130584367434988789" remote="130211100000000000" Dst="2" />
<file name="bartutex5.php" server="cemma-usc.net" local="130584367434998800" remote="130211100000000000" Dst="2" />
<file name="bartutex6.php" server="cemma-usc.net" local="130584367441573202" remote="130211100000000000" Dst="2" />
<file name="basic_contourex01.php" server="cemma-usc.net" local="130584367443144753" remote="130211100000000000" Dst="2" />
<file name="basic_contourex02.php" server="cemma-usc.net" local="130584367443144753" remote="130211100000000000" Dst="2" />
<file name="basic_contourex03-1.php" server="cemma-usc.net" local="130584367450319529" remote="130211100000000000" Dst="2" />
<file name="basic_contourex03-2.php" server="cemma-usc.net" local="130584367451900584" remote="130211100000000000" Dst="2" />
<file name="basic_contourex03-3.php" server="cemma-usc.net" local="130584367451900584" remote="130211100000000000" Dst="2" />
<file name="basic_contourex04.php" server="cemma-usc.net" local="130584367458156005" remote="130211100000000000" Dst="2" />
<file name="basic_contourex05.php" server="cemma-usc.net" local="130584367459677017" remote="130211100000000000" Dst="2" />
<file name="bezierex1.php" server="cemma-usc.net" local="130584367459677017" remote="130211100000000000" Dst="2" />
<file name="bkgimgflagex1.php" server="cemma-usc.net" local="130584367466721733" remote="130211100000000000" Dst="2" />
<file name="bkgimgflagex2.php" server="cemma-usc.net" local="130584367466721733" remote="130211100000000000" Dst="2" />
<file name="bkgimgflagex3.php" server="cemma-usc.net" local="130584367467602317" remote="130211100000000000" Dst="2" />
<file name="bkgimgflagex4.php" server="cemma-usc.net" local="130584367476178041" remote="130211100000000000" Dst="2" />
<file name="bkgimgflagex5.php" server="cemma-usc.net" local="130584367476178041" remote="130211100000000000" Dst="2" />
<file name="blueblack400x300grad.png" server="cemma-usc.net" local="130584367476978575" remote="130211100000000000" Dst="2" />
<file name="boxstockcsimex1.php" server="cemma-usc.net" local="130584367483753100" remote="130211100000000000" Dst="2" />
<file name="boxstockex1.php" server="cemma-usc.net" local="130584367485494263" remote="130211100000000000" Dst="2" />
<file name="boxstockex2.php" server="cemma-usc.net" local="130584367485494263" remote="130211100000000000" Dst="2" />
<file name="builtinplotmarksex1.php" server="cemma-usc.net" local="130584367492328827" remote="130211100000000000" Dst="2" />
<file name="canvas_jpgarchex.php" server="cemma-usc.net" local="130584367492328827" remote="130211100000000000" Dst="2" />
<file name="canvasbezierex1.php" server="cemma-usc.net" local="130584367493119355" remote="130211100000000000" Dst="2" />
<file name="canvasex01.php" server="cemma-usc.net" local="130584367499423443" remote="130211100000000000" Dst="2" />
<file name="canvasex02.php" server="cemma-usc.net" local="130584367501094539" remote="130211100000000000" Dst="2" />
<file name="canvasex03.php" server="cemma-usc.net" local="130584367501104546" remote="130211100000000000" Dst="2" />
<file name="canvasex04.php" server="cemma-usc.net" local="130584367507298679" remote="130211100000000000" Dst="2" />
<file name="canvasex05.php" server="cemma-usc.net" local="130584367508831371" remote="130211100000000000" Dst="2" />
<file name="canvasex06.php" server="cemma-usc.net" local="130584367508831371" remote="130211100000000000" Dst="2" />
<file name="canvaspiralex1.php" server="cemma-usc.net" local="130584367515946115" remote="130211100000000000" Dst="2" />
<file name="ccbp_ex1.php" server="cemma-usc.net" local="130584367515946115" remote="130211100000000000" Dst="2" />
<file name="ccbp_ex2.php" server="cemma-usc.net" local="130584367516726632" remote="130211100000000000" Dst="2" />
<file name="centeredlineex02.php" server="cemma-usc.net" local="130584367523493696" remote="130211100000000000" Dst="2" />
<file name="ccbpgraph.class.php" server="cemma-usc.net" local="130584367524294222" remote="130211100000000000" Dst="2" />
<file name="centeredlineex01.php" server="cemma-usc.net" local="130584367525224844" remote="130211100000000000" Dst="2" />
<file name="centeredlineex03.php" server="cemma-usc.net" local="130584367531102359" remote="130211100000000000" Dst="2" />
<file name="centerlinebarex1.php" server="cemma-usc.net" local="130584367532793488" remote="130211100000000000" Dst="2" />
<file name="checkgd.php" server="cemma-usc.net" local="130584367532793488" remote="130211100000000000" Dst="2" />
<file name="checkgd2.php" server="cemma-usc.net" local="130584367539618050" remote="130211100000000000" Dst="2" />
<file name="checkttf.php" server="cemma-usc.net" local="130584367540798831" remote="130211100000000000" Dst="2" />
<file name="classroom.jpg" server="cemma-usc.net" local="130584367541859551" remote="130211100000000000" Dst="2" />
<file name="clipping_ex1.php" server="cemma-usc.net" local="130584367545772752" remote="130211100000000000" Dst="2" />
<file name="clipping_ex2.php" server="cemma-usc.net" local="130584367548966286" remote="130211100000000000" Dst="2" />
<file name="colormaps.php" server="cemma-usc.net" local="130584367549876909" remote="130211100000000000" Dst="2" />
<file name="comb90dategraphex01.php" server="cemma-usc.net" local="130584367553739473" remote="130211100000000000" Dst="2" />
<file name="comb90dategraphex02.php" server="cemma-usc.net" local="130584367555965181" remote="130211100000000000" Dst="2" />
<file name="comb90dategraphex03.php" server="cemma-usc.net" local="130584367556846377" remote="130211100000000000" Dst="2" />
<file name="combgraphex1.php" server="cemma-usc.net" local="130584367561779675" remote="130211100000000000" Dst="2" />
<file name="combgraphex2.php" server="cemma-usc.net" local="130584367563971131" remote="130211100000000000" Dst="2" />
<file name="contourex01.php" server="cemma-usc.net" local="130584367564781696" remote="130211100000000000" Dst="2" />
<file name="contourex02.php" server="cemma-usc.net" local="130584367568504174" remote="130211100000000000" Dst="2" />
<file name="contourex03.php" server="cemma-usc.net" local="130584367570735653" remote="130211100000000000" Dst="2" />
<file name="contourex04.php" server="cemma-usc.net" local="130584367571616241" remote="130211100000000000" Dst="2" />
<file name="contourex05.php" server="cemma-usc.net" local="130584367576039195" remote="130211100000000000" Dst="2" />
<file name="csim_in_html_ex1.php" server="cemma-usc.net" local="130584367578530859" remote="130211100000000000" Dst="2" />
<file name="csim_in_html_ex2.php" server="cemma-usc.net" local="130584367579483913" remote="130211100000000000" Dst="2" />
<file name="csim_in_html_graph_ex1.php" server="cemma-usc.net" local="130584367584630944" remote="130211100000000000" Dst="2" />
<file name="csim_in_html_graph_ex2.php" server="cemma-usc.net" local="130584367587062560" remote="130211100000000000" Dst="2" />
<file name="dataset01.inc.php" server="cemma-usc.net" local="130584367588254165" remote="130211100000000000" Dst="2" />
<file name="dateaxisex1.php" server="cemma-usc.net" local="130584367593042404" remote="130211100000000000" Dst="2" />
<file name="dateaxisex2.php" server="cemma-usc.net" local="130584367595283897" remote="130211100000000000" Dst="2" />
<file name="dateaxisex3.php" server="cemma-usc.net" local="130584367596166195" remote="130211100000000000" Dst="2" />
<file name="dateaxisex4.php" server="cemma-usc.net" local="130584367600912457" remote="130211100000000000" Dst="2" />
<file name="datescaleticksex01.php" server="cemma-usc.net" local="130584367603244010" remote="130211100000000000" Dst="2" />
<file name="dateutilex01.php" server="cemma-usc.net" local="130584367604174640" remote="130211100000000000" Dst="2" />
<file name="dateutilex02.php" server="cemma-usc.net" local="130584367608031117" remote="130211100000000000" Dst="2" />
<file name="dupyaxisex1.php" server="cemma-usc.net" local="130584367610324802" remote="130211100000000000" Dst="2" />
<file name="example0-0.php" server="cemma-usc.net" local="130584367611215401" remote="130211100000000000" Dst="2" />
<file name="example0.php" server="cemma-usc.net" local="130584367615077985" remote="130211100000000000" Dst="2" />
<file name="example1.1.php" server="cemma-usc.net" local="130584367617449561" remote="130211100000000000" Dst="2" />
<file name="example1.2.php" server="cemma-usc.net" local="130584367618370728" remote="130211100000000000" Dst="2" />
<file name="example1.php" server="cemma-usc.net" local="130584367623179814" remote="130211100000000000" Dst="2" />
<file name="example10.php" server="cemma-usc.net" local="130584367625411300" remote="130211100000000000" Dst="2" />
<file name="example11.php" server="cemma-usc.net" local="130584367626472008" remote="130211100000000000" Dst="2" />
<file name="example13.php" server="cemma-usc.net" local="130584367630624786" remote="130211100000000000" Dst="2" />
<file name="example14.php" server="cemma-usc.net" local="130584367633196499" remote="130211100000000000" Dst="2" />
<file name="example15.php" server="cemma-usc.net" local="130584367634087090" remote="130211100000000000" Dst="2" />
<file name="example16.1.php" server="cemma-usc.net" local="130584367638911602" remote="130211100000000000" Dst="2" />
<file name="example16.2.php" server="cemma-usc.net" local="130584367641223146" remote="130211100000000000" Dst="2" />
<file name="example16.3.php" server="cemma-usc.net" local="130584367642063707" remote="130211100000000000" Dst="2" />
<file name="example16.4.php" server="cemma-usc.net" local="130584367645856252" remote="130211100000000000" Dst="2" />
<file name="example16.5.php" server="cemma-usc.net" local="130584367648325779" remote="130211100000000000" Dst="2" />
<file name="example16.6.php" server="cemma-usc.net" local="130584367649366450" remote="130211100000000000" Dst="2" />
<file name="example16.php" server="cemma-usc.net" local="130584367655352476" remote="130211100000000000" Dst="2" />
<file name="example17.php" server="cemma-usc.net" local="130584367655362486" remote="130211100000000000" Dst="2" />
<file name="example18.php" server="cemma-usc.net" local="130584367657797683" remote="130211100000000000" Dst="2" />
<file name="example19.1.php" server="cemma-usc.net" local="130584367662490809" remote="130211100000000000" Dst="2" />
<file name="example19.php" server="cemma-usc.net" local="130584367664922437" remote="130211100000000000" Dst="2" />
<file name="example2.1.php" server="cemma-usc.net" local="130584367666223298" remote="130211100000000000" Dst="2" />
<file name="example2.5.php" server="cemma-usc.net" local="130584367670836383" remote="130211100000000000" Dst="2" />
<file name="example2.6.php" server="cemma-usc.net" local="130584367673167940" remote="130211100000000000" Dst="2" />
<file name="example2.php" server="cemma-usc.net" local="130584367674248661" remote="130211100000000000" Dst="2" />
<file name="example20.1.php" server="cemma-usc.net" local="130584367678802614" remote="130211100000000000" Dst="2" />
<file name="example20.2.php" server="cemma-usc.net" local="130584367681124157" remote="130211100000000000" Dst="2" />
<file name="example20.3.php" server="cemma-usc.net" local="130584367682074792" remote="130211100000000000" Dst="2" />
<file name="example20.4.php" server="cemma-usc.net" local="130584367686627824" remote="130211100000000000" Dst="2" />
<file name="example20.5.php" server="cemma-usc.net" local="130584367688861048" remote="130211100000000000" Dst="2" />
<file name="example20.php" server="cemma-usc.net" local="130584367689741620" remote="130211100000000000" Dst="2" />
<file name="example21.php" server="cemma-usc.net" local="130584367694104538" remote="130211100000000000" Dst="2" />
<file name="example22.php" server="cemma-usc.net" local="130584367696356041" remote="130211100000000000" Dst="2" />
<file name="example23.php" server="cemma-usc.net" local="130584367697166598" remote="130211100000000000" Dst="2" />
<file name="example24.php" server="cemma-usc.net" local="130584367701304162" remote="130211100000000000" Dst="2" />
<file name="example25.1.php" server="cemma-usc.net" local="130584367704116044" remote="130211100000000000" Dst="2" />
<file name="example25.2.php" server="cemma-usc.net" local="130584367704996636" remote="130211100000000000" Dst="2" />
<file name="example25.php" server="cemma-usc.net" local="130584367709072771" remote="130211100000000000" Dst="2" />
<file name="example26.1.php" server="cemma-usc.net" local="130584367711454342" remote="130211100000000000" Dst="2" />
<file name="example26.php" server="cemma-usc.net" local="130584367712214853" remote="130211100000000000" Dst="2" />
<file name="example27.1.php" server="cemma-usc.net" local="130584367716227541" remote="130211100000000000" Dst="2" />
<file name="example27.2.php" server="cemma-usc.net" local="130584367716998052" remote="130211100000000000" Dst="2" />
<file name="example27.3.php" server="cemma-usc.net" local="130584367723003499" remote="130211100000000000" Dst="2" />
<file name="example27.php" server="cemma-usc.net" local="130584367724554519" remote="130211100000000000" Dst="2" />
<file name="example28.1.php" server="cemma-usc.net" local="130584367724564533" remote="130211100000000000" Dst="2" />
<file name="example28.2.php" server="cemma-usc.net" local="130584367731511496" remote="130211100000000000" Dst="2" />
<file name="example28.3.php" server="cemma-usc.net" local="130584367732972460" remote="130211100000000000" Dst="2" />
<file name="example28.php" server="cemma-usc.net" local="130584367732972460" remote="130211100000000000" Dst="2" />
<file name="example3.0.1.php" server="cemma-usc.net" local="130584367739476800" remote="130211100000000000" Dst="2" />
<file name="example3.0.2.php" server="cemma-usc.net" local="130584367740997820" remote="130211100000000000" Dst="2" />
<file name="example3.0.3.php" server="cemma-usc.net" local="130584367741007826" remote="130211100000000000" Dst="2" />
<file name="example3.1.1.php" server="cemma-usc.net" local="130584367747372783" remote="130211100000000000" Dst="2" />
<file name="example3.1.php" server="cemma-usc.net" local="130584367748843766" remote="130211100000000000" Dst="2" />
<file name="example3.2.1.php" server="cemma-usc.net" local="130584367748843766" remote="130211100000000000" Dst="2" />
<file name="example3.2.2.php" server="cemma-usc.net" local="130584367755428151" remote="130211100000000000" Dst="2" />
<file name="example3.2.php" server="cemma-usc.net" local="130584367756979179" remote="130211100000000000" Dst="2" />
<file name="example3.3.php" server="cemma-usc.net" local="130584367756979179" remote="130211100000000000" Dst="2" />
<file name="example3.4.1.php" server="cemma-usc.net" local="130584367763932959" remote="130211100000000000" Dst="2" />
<file name="example3.4.php" server="cemma-usc.net" local="130584367763932959" remote="130211100000000000" Dst="2" />
<file name="example3.php" server="cemma-usc.net" local="130584367764753508" remote="130211100000000000" Dst="2" />
<file name="example5.php" server="cemma-usc.net" local="130584367770847570" remote="130211100000000000" Dst="2" />
<file name="example4.php" server="cemma-usc.net" local="130584367771678128" remote="130211100000000000" Dst="2" />
<file name="example5.1.php" server="cemma-usc.net" local="130584367772428633" remote="130211100000000000" Dst="2" />
<file name="example6.1.php" server="cemma-usc.net" local="130584367778152448" remote="130211100000000000" Dst="2" />
<file name="example6.2.php" server="cemma-usc.net" local="130584367779688476" remote="130211100000000000" Dst="2" />
<file name="example6.php" server="cemma-usc.net" local="130584367779688476" remote="130211100000000000" Dst="2" />
<file name="example7.php" server="cemma-usc.net" local="130584367786142929" remote="130211100000000000" Dst="2" />
<file name="example8.1.php" server="cemma-usc.net" local="130584367787713982" remote="130211100000000000" Dst="2" />
<file name="example8.php" server="cemma-usc.net" local="130584367787713982" remote="130211100000000000" Dst="2" />
<file name="example9.1.php" server="cemma-usc.net" local="130584367794630834" remote="130211100000000000" Dst="2" />
<file name="example9.2.php" server="cemma-usc.net" local="130584367796241914" remote="130211100000000000" Dst="2" />
<file name="example9.php" server="cemma-usc.net" local="130584367796241914" remote="130211100000000000" Dst="2" />
<file name="exampleex9.php" server="cemma-usc.net" local="130584367802946940" remote="130211100000000000" Dst="2" />
<file name="fieldscatterex1.php" server="cemma-usc.net" local="130584367802946940" remote="130211100000000000" Dst="2" />
<file name="filledgridex1.php" server="cemma-usc.net" local="130584367803677432" remote="130211100000000000" Dst="2" />
<file name="filledline01.php" server="cemma-usc.net" local="130584367810201785" remote="130211100000000000" Dst="2" />
<file name="filledlineex01.1.php" server="cemma-usc.net" local="130584367811712802" remote="130211100000000000" Dst="2" />
<file name="filledlineex01.php" server="cemma-usc.net" local="130584367811722805" remote="130211100000000000" Dst="2" />
<file name="filledlineex02.php" server="cemma-usc.net" local="130584367817777871" remote="130211100000000000" Dst="2" />
<file name="filledlineex03.php" server="cemma-usc.net" local="130584367819529044" remote="130211100000000000" Dst="2" />
<file name="filledstepstyleex1.php" server="cemma-usc.net" local="130584367819529044" remote="130211100000000000" Dst="2" />
<file name="fixscale_radarex1.php" server="cemma-usc.net" local="130584367826763872" remote="130211100000000000" Dst="2" />
<file name="funcex1.php" server="cemma-usc.net" local="130584367826763872" remote="130211100000000000" Dst="2" />
<file name="footerex1.php" server="cemma-usc.net" local="130584367827494364" remote="130211100000000000" Dst="2" />
<file name="funcex2.php" server="cemma-usc.net" local="130584367833520400" remote="130211100000000000" Dst="2" />
<file name="funcex3.php" server="cemma-usc.net" local="130584367835131480" remote="130211100000000000" Dst="2" />
<file name="funcex4.php" server="cemma-usc.net" local="130584367835141490" remote="130211100000000000" Dst="2" />
<file name="gantt_samerowex1.php" server="cemma-usc.net" local="130584367842178794" remote="130211100000000000" Dst="2" />
<file name="gantt_samerowex2.php" server="cemma-usc.net" local="130584367842178794" remote="130211100000000000" Dst="2" />
<file name="gantt_textex1.php" server="cemma-usc.net" local="130584367842919277" remote="130211100000000000" Dst="2" />
<file name="ganttcolumnfontsex01.php" server="cemma-usc.net" local="130584367851157615" remote="130211100000000000" Dst="2" />
<file name="ganttconstrainex0.php" server="cemma-usc.net" local="130584367851157615" remote="130211100000000000" Dst="2" />
<file name="ganttconstrainex1.php" server="cemma-usc.net" local="130584367852108250" remote="130211100000000000" Dst="2" />
<file name="ganttconstrainex2.php" server="cemma-usc.net" local="130584367858559146" remote="130211100000000000" Dst="2" />
<file name="ganttcsimex01.php" server="cemma-usc.net" local="130584367860150208" remote="130211100000000000" Dst="2" />
<file name="ganttcsimex02.php" server="cemma-usc.net" local="130584367860150208" remote="130211100000000000" Dst="2" />
<file name="ganttex00.php" server="cemma-usc.net" local="130584367866654552" remote="130211100000000000" Dst="2" />
<file name="ganttex01.php" server="cemma-usc.net" local="130584367868255629" remote="130211100000000000" Dst="2" />
<file name="ganttex02.php" server="cemma-usc.net" local="130584367868255629" remote="130211100000000000" Dst="2" />
<file name="ganttex03.php" server="cemma-usc.net" local="130584367875810683" remote="130211100000000000" Dst="2" />
<file name="ganttex04.php" server="cemma-usc.net" local="130584367877281654" remote="130211100000000000" Dst="2" />
<file name="ganttex05.php" server="cemma-usc.net" local="130584367877281654" remote="130211100000000000" Dst="2" />
<file name="ganttex06.php" server="cemma-usc.net" local="130584367883687016" remote="130211100000000000" Dst="2" />
<file name="ganttex07.php" server="cemma-usc.net" local="130584367885248055" remote="130211100000000000" Dst="2" />
<file name="ganttex08.php" server="cemma-usc.net" local="130584367885248055" remote="130211100000000000" Dst="2" />
<file name="ganttex09.php" server="cemma-usc.net" local="130584367892196747" remote="130211100000000000" Dst="2" />
<file name="ganttex10.php" server="cemma-usc.net" local="130584367893677740" remote="130211100000000000" Dst="2" />
<file name="ganttex11.php" server="cemma-usc.net" local="130584367893687731" remote="130211100000000000" Dst="2" />
<file name="ganttex12.php" server="cemma-usc.net" local="130584367900751328" remote="130211100000000000" Dst="2" />
<file name="ganttex13-zoom1.php" server="cemma-usc.net" local="130584367900751328" remote="130211100000000000" Dst="2" />
<file name="ganttex13-zoom2.php" server="cemma-usc.net" local="130584367901521823" remote="130211100000000000" Dst="2" />
<file name="ganttex13.php" server="cemma-usc.net" local="130584367908522459" remote="130211100000000000" Dst="2" />
<file name="ganttex14.php" server="cemma-usc.net" local="130584367908522459" remote="130211100000000000" Dst="2" />
<file name="ganttex15.php" server="cemma-usc.net" local="130584367909277677" remote="130211100000000000" Dst="2" />
<file name="ganttex16.php" server="cemma-usc.net" local="130584367916142261" remote="130211100000000000" Dst="2" />
<file name="ganttex17-flag.php" server="cemma-usc.net" local="130584367916152268" remote="130211100000000000" Dst="2" />
<file name="ganttex17.php" server="cemma-usc.net" local="130584367916882756" remote="130211100000000000" Dst="2" />
<file name="ganttex18.php" server="cemma-usc.net" local="130584367923965593" remote="130211100000000000" Dst="2" />
<file name="ganttex19.php" server="cemma-usc.net" local="130584367923975599" remote="130211100000000000" Dst="2" />
<file name="ganttex30.php" server="cemma-usc.net" local="130584367924726109" remote="130211100000000000" Dst="2" />
<file name="ganttex_slice.php" server="cemma-usc.net" local="130584367933026670" remote="130211100000000000" Dst="2" />
<file name="gantthgridex1.php" server="cemma-usc.net" local="130584367933026670" remote="130211100000000000" Dst="2" />
<file name="gantthourex1.php" server="cemma-usc.net" local="130584367934017335" remote="130211100000000000" Dst="2" />
<file name="gantthourminex1.php" server="cemma-usc.net" local="130584367940606679" remote="130211100000000000" Dst="2" />
<file name="gantticonex1.php" server="cemma-usc.net" local="130584367942147684" remote="130211100000000000" Dst="2" />
<file name="ganttmonthyearex1.php" server="cemma-usc.net" local="130584367942147684" remote="130211100000000000" Dst="2" />
<file name="ganttmonthyearex2.php" server="cemma-usc.net" local="130584367949332499" remote="130211100000000000" Dst="2" />
<file name="ganttmonthyearex3.php" server="cemma-usc.net" local="130584367949332499" remote="130211100000000000" Dst="2" />
<file name="ganttmonthyearex4.php" server="cemma-usc.net" local="130584367950052964" remote="130211100000000000" Dst="2" />
<file name="ganttsimpleex1.php" server="cemma-usc.net" local="130584367956297134" remote="130211100000000000" Dst="2" />
<file name="grace_ex0.php" server="cemma-usc.net" local="130584367958058318" remote="130211100000000000" Dst="2" />
<file name="grace_ex1.php" server="cemma-usc.net" local="130584367958058318" remote="130211100000000000" Dst="2" />
<file name="grace_ex2.php" server="cemma-usc.net" local="130584367964202875" remote="130211100000000000" Dst="2" />
<file name="grace_ex3.php" server="cemma-usc.net" local="130584367965063454" remote="130211100000000000" Dst="2" />
<file name="gradbkgex1.php" server="cemma-usc.net" local="130584367965853978" remote="130211100000000000" Dst="2" />
<file name="gradlinefillex1.php" server="cemma-usc.net" local="130584367971199102" remote="130211100000000000" Dst="2" />
<file name="gradlinefillex2.php" server="cemma-usc.net" local="130584367972700101" remote="130211100000000000" Dst="2" />
<file name="gradlinefillex3.php" server="cemma-usc.net" local="130584367972710095" remote="130211100000000000" Dst="2" />
<file name="gradlinefillex4.php" server="cemma-usc.net" local="130584367979834850" remote="130211100000000000" Dst="2" />
<file name="groupbarex1.php" server="cemma-usc.net" local="130584367980635388" remote="130211100000000000" Dst="2" />
<file name="heat1.jpg" server="cemma-usc.net" local="130584367981713118" remote="130211100000000000" Dst="2" />
<file name="horizbarex1.php" server="cemma-usc.net" local="130584367987000132" remote="130211100000000000" Dst="2" />
<file name="horizbarex2.php" server="cemma-usc.net" local="130584367990362358" remote="130211100000000000" Dst="2" />
<file name="horizbarex3.php" server="cemma-usc.net" local="130584367991282977" remote="130211100000000000" Dst="2" />
<file name="horizbarex4.php" server="cemma-usc.net" local="130584367995156167" remote="130211100000000000" Dst="2" />
<file name="imgmarkercsimex1.php" server="cemma-usc.net" local="130584367998949142" remote="130211100000000000" Dst="2" />
<file name="imgmarkerex1.php" server="cemma-usc.net" local="130584367999689640" remote="130211100000000000" Dst="2" />
<file name="horizbarex6.php" server="cemma-usc.net" local="130584368000550219" remote="130211100000000000" Dst="2" />
<file name="impulsex1.php" server="cemma-usc.net" local="130584368004232667" remote="130211100000000000" Dst="2" />
<file name="impulsex2.php" server="cemma-usc.net" local="130584368006514186" remote="130211100000000000" Dst="2" />
<file name="impulsex3.php" server="cemma-usc.net" local="130584368007484846" remote="130211100000000000" Dst="2" />
<file name="impulsex4.php" server="cemma-usc.net" local="130584368011588830" remote="130211100000000000" Dst="2" />
<file name="interpolation-growth-log.php" server="cemma-usc.net" local="130584368013980431" remote="130211100000000000" Dst="2" />
<file name="interpolation-growth.php" server="cemma-usc.net" local="130584368015241273" remote="130211100000000000" Dst="2" />
<file name="inyaxisex1.php" server="cemma-usc.net" local="130584368019213922" remote="130211100000000000" Dst="2" />
<file name="inyaxisex2.php" server="cemma-usc.net" local="130584368022245963" remote="130211100000000000" Dst="2" />
<file name="inyaxisex3.php" server="cemma-usc.net" local="130584368023346706" remote="130211100000000000" Dst="2" />
<file name="ledex1.php" server="cemma-usc.net" local="130584368028260082" remote="130211100000000000" Dst="2" />
<file name="ledex10.php" server="cemma-usc.net" local="130584368030884280" remote="130211100000000000" Dst="2" />
<file name="ledex11.php" server="cemma-usc.net" local="130584368031957265" remote="130211100000000000" Dst="2" />
<file name="ledex12.php" server="cemma-usc.net" local="130584368036930591" remote="130211100000000000" Dst="2" />
<file name="ledex13.php" server="cemma-usc.net" local="130584368039252137" remote="130211100000000000" Dst="2" />
<file name="ledex14.php" server="cemma-usc.net" local="130584368040043344" remote="130211100000000000" Dst="2" />
<file name="ledex15.php" server="cemma-usc.net" local="130584368044468402" remote="130211100000000000" Dst="2" />
<file name="ledex16.php" server="cemma-usc.net" local="130584368046819976" remote="130211100000000000" Dst="2" />
<file name="ledex17.php" server="cemma-usc.net" local="130584368047690550" remote="130211100000000000" Dst="2" />
<file name="ledex2.php" server="cemma-usc.net" local="130584368051384192" remote="130211100000000000" Dst="2" />
<file name="ledex3.php" server="cemma-usc.net" local="130584368053815804" remote="130211100000000000" Dst="2" />
<file name="ledex4.1.php" server="cemma-usc.net" local="130584368054786468" remote="130211100000000000" Dst="2" />
<file name="ledex4.2.php" server="cemma-usc.net" local="130584368058639026" remote="130211100000000000" Dst="2" />
<file name="ledex4.php" server="cemma-usc.net" local="130584368060970583" remote="130211100000000000" Dst="2" />
<file name="ledex5.php" server="cemma-usc.net" local="130584368061801512" remote="130211100000000000" Dst="2" />
<file name="ledex6.php" server="cemma-usc.net" local="130584368066554691" remote="130211100000000000" Dst="2" />
<file name="ledex7.php" server="cemma-usc.net" local="130584368069248324" remote="130211100000000000" Dst="2" />
<file name="ledex8.php" server="cemma-usc.net" local="130584368070519173" remote="130211100000000000" Dst="2" />
<file name="ledex9.php" server="cemma-usc.net" local="130584368075523939" remote="130211100000000000" Dst="2" />
<file name="ledex_cyrillic.php" server="cemma-usc.net" local="130584368077965562" remote="130211100000000000" Dst="2" />
<file name="ledex_cyrillic2.php" server="cemma-usc.net" local="130584368078796125" remote="130211100000000000" Dst="2" />
<file name="lightbluedarkblue400x300grad.png" server="cemma-usc.net" local="130584368084358099" remote="130211100000000000" Dst="2" />
<file name="linebarcentex1.php" server="cemma-usc.net" local="130584368087049905" remote="130211100000000000" Dst="2" />
<file name="linebarex1.php" server="cemma-usc.net" local="130584368087900477" remote="130211100000000000" Dst="2" />
<file name="linebarex2.php" server="cemma-usc.net" local="130584368093421075" remote="130211100000000000" Dst="2" />
<file name="linebarex3.php" server="cemma-usc.net" local="130584368095982762" remote="130211100000000000" Dst="2" />
<file name="linegraceex.php" server="cemma-usc.net" local="130584368096883364" remote="130211100000000000" Dst="2" />
<file name="lineiconex1.php" server="cemma-usc.net" local="130584368101900825" remote="130211100000000000" Dst="2" />
<file name="lineiconex2.php" server="cemma-usc.net" local="130584368104302429" remote="130211100000000000" Dst="2" />
<file name="lineimagefillex1.php" server="cemma-usc.net" local="130584368105183013" remote="130211100000000000" Dst="2" />
<file name="linlogex1.php" server="cemma-usc.net" local="130584368109275747" remote="130211100000000000" Dst="2" />
<file name="listallflags.php" server="cemma-usc.net" local="130584368110176348" remote="130211100000000000" Dst="2" />
<file name="listallflags_helper.php" server="cemma-usc.net" local="130584368115850141" remote="130211100000000000" Dst="2" />
<file name="listfontsex1.php" server="cemma-usc.net" local="130584368117361158" remote="130211100000000000" Dst="2" />
<file name="logbarex1.php" server="cemma-usc.net" local="130584368117371157" remote="130211100000000000" Dst="2" />
<file name="loglogex1.php" server="cemma-usc.net" local="130584368124741440" remote="130211100000000000" Dst="2" />
<file name="manscaleex1.php" server="cemma-usc.net" local="130584368124751439" remote="130211100000000000" Dst="2" />
<file name="manscaleex2.php" server="cemma-usc.net" local="130584368125531960" remote="130211100000000000" Dst="2" />
<file name="manscaleex3.php" server="cemma-usc.net" local="130584368132080831" remote="130211100000000000" Dst="2" />
<file name="manscaleex4.php" server="cemma-usc.net" local="130584368133681904" remote="130211100000000000" Dst="2" />
<file name="manual_textscale_ex1.php" server="cemma-usc.net" local="130584368133681904" remote="130211100000000000" Dst="2" />
<file name="manual_textscale_ex2.php" server="cemma-usc.net" local="130584368139808086" remote="130211100000000000" Dst="2" />
<file name="manual_textscale_ex3.php" server="cemma-usc.net" local="130584368141339101" remote="130211100000000000" Dst="2" />
<file name="manual_textscale_ex4.php" server="cemma-usc.net" local="130584368141339101" remote="130211100000000000" Dst="2" />
<file name="manualtickex1.php" server="cemma-usc.net" local="130584368148744066" remote="130211100000000000" Dst="2" />
<file name="manualtickex1a.php" server="cemma-usc.net" local="130584368148754053" remote="130211100000000000" Dst="2" />
<file name="manualtickex2.php" server="cemma-usc.net" local="130584368149494559" remote="130211100000000000" Dst="2" />
<file name="manualtickex3.php" server="cemma-usc.net" local="130584368156849463" remote="130211100000000000" Dst="2" />
<file name="manualtickex4.php" server="cemma-usc.net" local="130584368156849463" remote="130211100000000000" Dst="2" />
<file name="markflagex1.php" server="cemma-usc.net" local="130584368157650006" remote="130211100000000000" Dst="2" />
<file name="mkgrad.php" server="cemma-usc.net" local="130584368164624980" remote="130211100000000000" Dst="2" />
<file name="multconstganttex01.php" server="cemma-usc.net" local="130584368166366139" remote="130211100000000000" Dst="2" />
<file name="mulyaxiscsimex1.php" server="cemma-usc.net" local="130584368166376141" remote="130211100000000000" Dst="2" />
<file name="mulyaxisex1.php" server="cemma-usc.net" local="130584368173555445" remote="130211100000000000" Dst="2" />
<file name="negbarvalueex01.php" server="cemma-usc.net" local="130584368174355984" remote="130211100000000000" Dst="2" />
<file name="nullvalueex01.php" server="cemma-usc.net" local="130584368176687529" remote="130211100000000000" Dst="2" />
<file name="partiallyfilledlineex1.php" server="cemma-usc.net" local="130584368177768251" remote="130211100000000000" Dst="2" />
<file name="penguin.png" server="cemma-usc.net" local="130584368183392010" remote="130211100000000000" Dst="2" />
<file name="pie3d_csimex1.php" server="cemma-usc.net" local="130584368186043793" remote="130211100000000000" Dst="2" />
<file name="pie3dex1.php" server="cemma-usc.net" local="130584368187094491" remote="130211100000000000" Dst="2" />
<file name="pie3dex2.php" server="cemma-usc.net" local="130584368192067797" remote="130211100000000000" Dst="2" />
<file name="pie3dex3.php" server="cemma-usc.net" local="130584368194339314" remote="130211100000000000" Dst="2" />
<file name="pie3dex4.php" server="cemma-usc.net" local="130584368195249922" remote="130211100000000000" Dst="2" />
<file name="pie3dex5.php" server="cemma-usc.net" local="130584368199825068" remote="130211100000000000" Dst="2" />
<file name="pie_csimex1.php" server="cemma-usc.net" local="130584368202036541" remote="130211100000000000" Dst="2" />
<file name="piebkgex1.php" server="cemma-usc.net" local="130584368202927156" remote="130211100000000000" Dst="2" />
<file name="piec_csimex1.php" server="cemma-usc.net" local="130584368207390120" remote="130211100000000000" Dst="2" />
<file name="piecex1.php" server="cemma-usc.net" local="130584368209910001" remote="130211100000000000" Dst="2" />
<file name="piecex2.php" server="cemma-usc.net" local="130584368210940705" remote="130211100000000000" Dst="2" />
<file name="pieex1.php" server="cemma-usc.net" local="130584368215193533" remote="130211100000000000" Dst="2" />
<file name="pieex2.php" server="cemma-usc.net" local="130584368217775273" remote="130211100000000000" Dst="2" />
<file name="pieex3.php" server="cemma-usc.net" local="130584368218595821" remote="130211100000000000" Dst="2" />
<file name="pieex4.php" server="cemma-usc.net" local="130584368223289445" remote="130211100000000000" Dst="2" />
<file name="pieex5.php" server="cemma-usc.net" local="130584368225500902" remote="130211100000000000" Dst="2" />
<file name="pieex6.php" server="cemma-usc.net" local="130584368226331457" remote="130211100000000000" Dst="2" />
<file name="pieex7.php" server="cemma-usc.net" local="130584368231008861" remote="130211100000000000" Dst="2" />
<file name="pieex8.php" server="cemma-usc.net" local="130584368233640610" remote="130211100000000000" Dst="2" />
<file name="pieex9.php" server="cemma-usc.net" local="130584368234481176" remote="130211100000000000" Dst="2" />
<file name="pielabelsex1.php" server="cemma-usc.net" local="130584368238224717" remote="130211100000000000" Dst="2" />
<file name="pielabelsex2.php" server="cemma-usc.net" local="130584368240509138" remote="130211100000000000" Dst="2" />
<file name="pielabelsex3.php" server="cemma-usc.net" local="130584368241299670" remote="130211100000000000" Dst="2" />
<file name="pielabelsex4.php" server="cemma-usc.net" local="130584368245782656" remote="130211100000000000" Dst="2" />
<file name="pielabelsex5.php" server="cemma-usc.net" local="130584368247994844" remote="130211100000000000" Dst="2" />
<file name="plotbanddensity_ex0.php" server="cemma-usc.net" local="130584368248885431" remote="130211100000000000" Dst="2" />
<file name="plotbanddensity_ex1.php" server="cemma-usc.net" local="130584368253408609" remote="130211100000000000" Dst="2" />
<file name="plotbanddensity_ex2.php" server="cemma-usc.net" local="130584368255600073" remote="130211100000000000" Dst="2" />
<file name="plotlineex1.php" server="cemma-usc.net" local="130584368256490668" remote="130211100000000000" Dst="2" />
<file name="polar_csimex1.php" server="cemma-usc.net" local="130584368260957047" remote="130211100000000000" Dst="2" />
<file name="polarclockex1.php" server="cemma-usc.net" local="130584368263288600" remote="130211100000000000" Dst="2" />
<file name="polarclockex2.php" server="cemma-usc.net" local="130584368264149175" remote="130211100000000000" Dst="2" />
<file name="polarex0-180.php" server="cemma-usc.net" local="130584368268932365" remote="130211100000000000" Dst="2" />
<file name="polarex0.php" server="cemma-usc.net" local="130584368271164037" remote="130211100000000000" Dst="2" />
<file name="polarex1.php" server="cemma-usc.net" local="130584368272034634" remote="130211100000000000" Dst="2" />
<file name="polarex10.php" server="cemma-usc.net" local="130584368275857183" remote="130211100000000000" Dst="2" />
<file name="polarex2.php" server="cemma-usc.net" local="130584368278328834" remote="130211100000000000" Dst="2" />
<file name="polarex3-lin.php" server="cemma-usc.net" local="130584368279359519" remote="130211100000000000" Dst="2" />
<file name="polarex3.php" server="cemma-usc.net" local="130584368283132046" remote="130211100000000000" Dst="2" />
<file name="polarex4.php" server="cemma-usc.net" local="130584368285353522" remote="130211100000000000" Dst="2" />
<file name="polarex5.php" server="cemma-usc.net" local="130584368286344179" remote="130211100000000000" Dst="2" />
<file name="polarex6.php" server="cemma-usc.net" local="130584368292458259" remote="130211100000000000" Dst="2" />
<file name="polarex7-1.php" server="cemma-usc.net" local="130584368294944077" remote="130211100000000000" Dst="2" />
<file name="polarex7-2.php" server="cemma-usc.net" local="130584368295764621" remote="130211100000000000" Dst="2" />
<file name="polarex7.php" server="cemma-usc.net" local="130584368299497109" remote="130211100000000000" Dst="2" />
<file name="polarex8.php" server="cemma-usc.net" local="130584368301710813" remote="130211100000000000" Dst="2" />
<file name="polarex9.php" server="cemma-usc.net" local="130584368302553079" remote="130211100000000000" Dst="2" />
<file name="prepaccdata_example.php" server="cemma-usc.net" local="130584368306256428" remote="130211100000000000" Dst="2" />
<file name="pushpinex1.php" server="cemma-usc.net" local="130584368308487899" remote="130211100000000000" Dst="2" />
<file name="pushpinex2.php" server="cemma-usc.net" local="130584368309388508" remote="130211100000000000" Dst="2" />
<file name="radar_csimex1.php" server="cemma-usc.net" local="130584368313141492" remote="130211100000000000" Dst="2" />
<file name="radarex1.php" server="cemma-usc.net" local="130584368315413005" remote="130211100000000000" Dst="2" />
<file name="radarex2.php" server="cemma-usc.net" local="130584368316323617" remote="130211100000000000" Dst="2" />
<file name="radarex3.php" server="cemma-usc.net" local="130584368320206206" remote="130211100000000000" Dst="2" />
<file name="radarex4.php" server="cemma-usc.net" local="130584368322517774" remote="130211100000000000" Dst="2" />
<file name="radarex5.php" server="cemma-usc.net" local="130584368323558875" remote="130211100000000000" Dst="2" />
<file name="radarex6.1.php" server="cemma-usc.net" local="130584368328552194" remote="130211100000000000" Dst="2" />
<file name="radarex6.php" server="cemma-usc.net" local="130584368330963813" remote="130211100000000000" Dst="2" />
<file name="radarex7.php" server="cemma-usc.net" local="130584368331704311" remote="130211100000000000" Dst="2" />
<file name="radarex8.1.php" server="cemma-usc.net" local="130584368335474794" remote="130211100000000000" Dst="2" />
<file name="radarex8.php" server="cemma-usc.net" local="130584368337879461" remote="130211100000000000" Dst="2" />
<file name="radarex9.php" server="cemma-usc.net" local="130584368338760037" remote="130211100000000000" Dst="2" />
<file name="radarlogex1-aa.php" server="cemma-usc.net" local="130584368342853007" remote="130211100000000000" Dst="2" />
<file name="radarlogex1.php" server="cemma-usc.net" local="130584368345305541" remote="130211100000000000" Dst="2" />
<file name="radarlogex2.php" server="cemma-usc.net" local="130584368346706473" remote="130211100000000000" Dst="2" />
<file name="radarmarkex1.php" server="cemma-usc.net" local="130584368352000004" remote="130211100000000000" Dst="2" />
<file name="rotateex1.php" server="cemma-usc.net" local="130584368354451641" remote="130211100000000000" Dst="2" />
<file name="rotex0.php" server="cemma-usc.net" local="130584368355334239" remote="130211100000000000" Dst="2" />
<file name="rotex1.php" server="cemma-usc.net" local="130584368359366932" remote="130211100000000000" Dst="2" />
<file name="rotex2.php" server="cemma-usc.net" local="130584368361578401" remote="130211100000000000" Dst="2" />
<file name="rotex3.php" server="cemma-usc.net" local="130584368362448986" remote="130211100000000000" Dst="2" />
<file name="rotex4.php" server="cemma-usc.net" local="130584368368075521" remote="130211100000000000" Dst="2" />
<file name="rotex5.php" server="cemma-usc.net" local="130584368368075521" remote="130211100000000000" Dst="2" />
<file name="saab_95.jpg" server="cemma-usc.net" local="130584368371437766" remote="130211100000000000" Dst="2" />
<file name="scatter_csimex1.php" server="cemma-usc.net" local="130584368375162870" remote="130211100000000000" Dst="2" />
<file name="scatterex1.php" server="cemma-usc.net" local="130584368378204909" remote="130211100000000000" Dst="2" />
<file name="scatterex2.php" server="cemma-usc.net" local="130584368378975416" remote="130211100000000000" Dst="2" />
<file name="scatterlinkex1.php" server="cemma-usc.net" local="130584368382858017" remote="130211100000000000" Dst="2" />
<file name="scatterlinkex2.php" server="cemma-usc.net" local="130584368385350407" remote="130211100000000000" Dst="2" />
<file name="scatterlinkex3.php" server="cemma-usc.net" local="130584368386140935" remote="130211100000000000" Dst="2" />
<file name="scatterlinkex4.php" server="cemma-usc.net" local="130584368390734531" remote="130211100000000000" Dst="2" />
<file name="scatterrotex1.php" server="cemma-usc.net" local="130584368392946028" remote="130211100000000000" Dst="2" />
<file name="show-example.php" server="cemma-usc.net" local="130584368393896778" remote="130211100000000000" Dst="2" />
<file name="show-image.php" server="cemma-usc.net" local="130584368398312093" remote="130211100000000000" Dst="2" />
<file name="show-source.php" server="cemma-usc.net" local="130584368400613630" remote="130211100000000000" Dst="2" />
<file name="smallstaticbandsex1.php" server="cemma-usc.net" local="130584368401634324" remote="130211100000000000" Dst="2" />
<file name="smallstaticbandsex10.php" server="cemma-usc.net" local="130584368406481304" remote="130211100000000000" Dst="2" />
<file name="smallstaticbandsex11.php" server="cemma-usc.net" local="130584368408902906" remote="130211100000000000" Dst="2" />
<file name="smallstaticbandsex2.php" server="cemma-usc.net" local="130584368409913581" remote="130211100000000000" Dst="2" />
<file name="smallstaticbandsex3.php" server="cemma-usc.net" local="130584368417488644" remote="130211100000000000" Dst="2" />
<file name="smallstaticbandsex4.php" server="cemma-usc.net" local="130584368421281781" remote="130211100000000000" Dst="2" />
<file name="smallstaticbandsex5.php" server="cemma-usc.net" local="130584368422143713" remote="130211100000000000" Dst="2" />
<file name="smallstaticbandsex6.php" server="cemma-usc.net" local="130584368426736781" remote="130211100000000000" Dst="2" />
<file name="smallstaticbandsex7.php" server="cemma-usc.net" local="130584368428988304" remote="130211100000000000" Dst="2" />
<file name="smallstaticbandsex8.php" server="cemma-usc.net" local="130584368429800918" remote="130211100000000000" Dst="2" />
<file name="smallstaticbandsex9.php" server="cemma-usc.net" local="130584368433543141" remote="130211100000000000" Dst="2" />
<file name="splineex1.php" server="cemma-usc.net" local="130584368436114855" remote="130211100000000000" Dst="2" />
<file name="staticbandbarex1.php" server="cemma-usc.net" local="130584368437005453" remote="130211100000000000" Dst="2" />
<file name="staticbandbarex2.php" server="cemma-usc.net" local="130584368441711496" remote="130211100000000000" Dst="2" />
<file name="staticbandbarex3.php" server="cemma-usc.net" local="130584368443862928" remote="130211100000000000" Dst="2" />
<file name="staticbandbarex4.php" server="cemma-usc.net" local="130584368444823574" remote="130211100000000000" Dst="2" />
<file name="staticbandbarex5.php" server="cemma-usc.net" local="130584368449606776" remote="130211100000000000" Dst="2" />
<file name="staticbandbarex6.php" server="cemma-usc.net" local="130584368455230520" remote="130211100000000000" Dst="2" />
<file name="staticlinebarex1.php" server="cemma-usc.net" local="130584368459806803" remote="130211100000000000" Dst="2" />
<file name="staticbandbarex7.php" server="cemma-usc.net" local="130584368461384176" remote="130211100000000000" Dst="2" />
<file name="stockex1.php" server="cemma-usc.net" local="130584368461394183" remote="130211100000000000" Dst="2" />
<file name="stockex2.php" server="cemma-usc.net" local="130584368468510683" remote="130211100000000000" Dst="2" />
<file name="sunspotsex1.php" server="cemma-usc.net" local="130584368469531361" remote="130211100000000000" Dst="2" />
<file name="stship.jpg" server="cemma-usc.net" local="130584368470291873" remote="130211100000000000" Dst="2" />
<file name="sunspotsex2.php" server="cemma-usc.net" local="130584368476486014" remote="130211100000000000" Dst="2" />
<file name="sunspotsex3.php" server="cemma-usc.net" local="130584368478227173" remote="130211100000000000" Dst="2" />
<file name="sunspotsex4.php" server="cemma-usc.net" local="130584368478237171" remote="130211100000000000" Dst="2" />
<file name="sunspotsex5.php" server="cemma-usc.net" local="130584368485193154" remote="130211100000000000" Dst="2" />
<file name="sunspotsex6.php" server="cemma-usc.net" local="130584368485193154" remote="130211100000000000" Dst="2" />
<file name="sunspotsex7.php" server="cemma-usc.net" local="130584368486083773" remote="130211100000000000" Dst="2" />
<file name="text-example1.php" server="cemma-usc.net" local="130584368492798257" remote="130211100000000000" Dst="2" />
<file name="testsuit.php" server="cemma-usc.net" local="130584368493578774" remote="130211100000000000" Dst="2" />
<file name="tabtitleex1.php" server="cemma-usc.net" local="130584368494319277" remote="130211100000000000" Dst="2" />
<file name="text-example2.php" server="cemma-usc.net" local="130584368499792928" remote="130211100000000000" Dst="2" />
<file name="textalignex1.php" server="cemma-usc.net" local="130584368501323955" remote="130211100000000000" Dst="2" />
<file name="textpalignex1.php" server="cemma-usc.net" local="130584368501323955" remote="130211100000000000" Dst="2" />
<file name="tiger1.jpg" server="cemma-usc.net" local="130584368510720226" remote="130211100000000000" Dst="2" />
<file name="tiger_bkg.gif" server="cemma-usc.net" local="130584368510720226" remote="130211100000000000" Dst="2" />
<file name="tiger_bkg.jpg" server="cemma-usc.net" local="130584368511500751" remote="130211100000000000" Dst="2" />
<file name="timestampex01.php" server="cemma-usc.net" local="130584368519005787" remote="130211100000000000" Dst="2" />
<file name="tiger_bkg.png" server="cemma-usc.net" local="130584368520496751" remote="130211100000000000" Dst="2" />
<file name="titlecsimex01.php" server="cemma-usc.net" local="130584368520496751" remote="130211100000000000" Dst="2" />
<file name="titleex1.php" server="cemma-usc.net" local="130584368528085614" remote="130211100000000000" Dst="2" />
<file name="topxaxisex1.php" server="cemma-usc.net" local="130584368529206367" remote="130211100000000000" Dst="2" />
<file name="worldmap1.jpg" server="cemma-usc.net" local="130584368534910172" remote="130211100000000000" Dst="2" />
<file name="y2synch.php" server="cemma-usc.net" local="130584368534910172" remote="130211100000000000" Dst="2" />
<file name="y2synch2.php" server="cemma-usc.net" local="130584368535710715" remote="130211100000000000" Dst="2" />
<file name="yearssn.txt" server="cemma-usc.net" local="130584368542437440" remote="130211100000000000" Dst="2" />
</dwsync>